finol/__init__.py
finol/config.py
finol/setup.py
finol/utils.py
finol/benchmark_results/__init__.py
finol/data_layer/__init__.py
finol/data_layer/data_collector.py
finol/data_layer/data_loader.py
finol/data_layer/date_index_merge.py
finol/data_layer/scaler_selector.py
finol/evaluation_layer/__init__.py
finol/evaluation_layer/benchmark_loader.py
finol/evaluation_layer/metric_caculator.py
finol/evaluation_layer/model_evaluator.py
finol/model_layer/CNN.py
finol/model_layer/DNN.py
finol/model_layer/LSRE_CAAN.py
finol/model_layer/LSTM.py
finol/model_layer/RNN.py
finol/model_layer/Transformer.py
finol/model_layer/__init__.py
finol/model_layer/model_selector.py
finol/optimization_layer/__init__.py
finol/optimization_layer/criterion_selector.py
finol/optimization_layer/model_trainer.py
finol/optimization_layer/optimizer_selector.py
finol/update/__init__.py
finol-0.0.1.dist-info/LICENSE
finol-0.0.1.dist-info/METADATA
finol-0.0.1.dist-info/WHEEL
finol-0.0.1.dist-info/top_level.txt
finol-0.0.1.dist-info/RECORD
