Metadata-Version: 2.1
Name: finol
Version: 0.0.1
Summary: A plug-and-play Python library for data-driven OLPS research
Home-page: https://github.com/jiahaoli57/FinOL
Author: Jiahao Li
Author-email: finol.official@gmail.com
License: MIT
Classifier: License :: OSI Approved :: MIT License
Classifier: Programming Language :: Python
Classifier: Programming Language :: Python :: 3
Classifier: Programming Language :: Python :: 3.9
Classifier: Programming Language :: Python :: Implementation :: CPython
Classifier: Programming Language :: Python :: Implementation :: PyPy
Requires-Python: >=3.9.0
License-File: LICENSE
